reflex_echarts/__init__.py
reflex_echarts/echarts.py
reflex_echarts-0.1.0.dist-info/METADATA
reflex_echarts-0.1.0.dist-info/WHEEL
reflex_echarts-0.1.0.dist-info/top_level.txt
reflex_echarts-0.1.0.dist-info/RECORD
