Metadata-Version: 2.2
Name: reflex-echarts
Version: 0.1.0
Summary: Reflex Wrapper for echarts-for-react library.
Author-email: Masen Furer <m_github@0x26.net>
License: Apache-2.0
Project-URL: Homepage, https://github.com/masenf/react-echarts
Keywords: reflex,reflex-custom-components
Classifier: Development Status :: 4 - Beta
Requires-Python: >=3.10
Requires-Dist: reflex>=0.6.8
Provides-Extra: dev
Requires-Dist: build; extra == "dev"
Requires-Dist: twine; extra == "dev"
